{
  "version": "5.1.0",
  "flags": {},
  "shapes": [
    {
      "label": "z",
      "points": [
        [
          0,
          735
        ],
        [
          1,
          736
        ],
        [
          170,
          772
        ],
        [
          417,
          807
        ],
        [
          449,
          463
        ],
        [
          333,
          274
        ],
        [
          225,
          54
        ],
        [
          199,
          0
        ],
        [
          0,
          0
        ],
        [
          0,
          735
        ]
      ],
      "group_id": null,
      "shape_type": "polygon",
      "flags": {}
    },
    {
      "label": "zx",
      "points": [
        [
          201,
          0
        ],
        [
          226,
          54
        ],
        [
          334,
          275
        ],
        [
          449,
          466
        ],
        [
          523,
          415
        ],
        [
          460,
          236
        ],
        [
          389,
          0
        ],
        [
          201,
          0
        ]
      ],
      "group_id": null,
      "shape_type": "polygon",
      "flags": {}
    },
    {
      "label": "s",
      "points": [
        [
          390,
          0
        ],
        [
          459,
          236
        ],
        [
          523,
          415
        ],
        [
          1020,
          478
        ],
        [
          1352,
          104
        ],
        [
          1449,
          0
        ],
        [
          390,
          0
        ]
      ],
      "group_id": null,
      "shape_type": "polygon",
      "flags": {}
    },
    {
      "label": "yx",
      "points": [
        [
          1450,
          0
        ],
        [
          1353,
          105
        ],
        [
          1021,
          476
        ],
        [
          1088,
          545
        ],
        [
          1480,
          238
        ],
        [
          1757,
          0
        ],
        [
          1450,
          0
        ]
      ],
      "group_id": null,
      "shape_type": "polygon",
      "flags": {}
    },
    {
      "label": "y",
      "points": [
        [
          1920,
          0
        ],
        [
          1759,
          0
        ],
        [
          1489,
          232
        ],
        [
          1396,
          301
        ],
        [
          1088,
          545
        ],
        [
          1074,
          884
        ],
        [
          1322,
          900
        ],
        [
          1591,
          909
        ],
        [
          1920,
          878
        ],
        [
          1920,
          0
        ]
      ],
      "group_id": null,
      "shape_type": "polygon",
      "flags": {}
    },
    {
      "label": "x",
      "points": [
        [
          0,
          1080
        ],
        [
          1920,
          1080
        ],
        [
          1920,
          878
        ],
        [
          1592,
          910
        ],
        [
          1321,
          903
        ],
        [
          1072,
          884
        ],
        [
          419,
          806
        ],
        [
          170,
          772
        ],
        [
          0,
          734
        ],
        [
          0,
          1080
        ]
      ],
      "group_id": null,
      "shape_type": "polygon",
      "flags": {}
    }
  ],
  "imagePath": "12-5.jpg",
  "imageData": null,
  "imageHeight": 1080,
  "imageWidth": 1920
}