{
  "version": "5.1.0",
  "flags": {},
  "shapes": [
    {
      "label": "z",
      "points": [
        [
          0,
          781
        ],
        [
          170,
          818
        ],
        [
          464,
          858
        ],
        [
          835,
          875
        ],
        [
          846,
          566
        ],
        [
          785,
          502
        ],
        [
          545,
          207
        ],
        [
          378,
          0
        ],
        [
          0,
          0
        ],
        [
          0,
          781
        ]
      ],
      "group_id": null,
      "shape_type": "polygon",
      "flags": {}
    },
    {
      "label": "zx",
      "points": [
        [
          378,
          0
        ],
        [
          543,
          204
        ],
        [
          786,
          502
        ],
        [
          847,
          565
        ],
        [
          913,
          511
        ],
        [
          760,
          220
        ],
        [
          643,
          0
        ],
        [
          378,
          0
        ]
      ],
      "group_id": null,
      "shape_type": "polygon",
      "flags": {}
    },
    {
      "label": "s",
      "points": [
        [
          914,
          511
        ],
        [
          1403,
          517
        ],
        [
          1571,
          269
        ],
        [
          1727,
          0
        ],
        [
          645,
          2
        ],
        [
          760,
          218
        ],
        [
          914,
          511
        ]
      ],
      "group_id": null,
      "shape_type": "polygon",
      "flags": {}
    },
    {
      "label": "yx",
      "points": [
        [
          1676,
          355
        ],
        [
          1840,
          162
        ],
        [
          1920,
          48
        ],
        [
          1918,
          1
        ],
        [
          1726,
          0
        ],
        [
          1660,
          115
        ],
        [
          1570,
          272
        ],
        [
          1403,
          515
        ],
        [
          1464,
          568
        ],
        [
          1676,
          355
        ]
      ],
      "group_id": null,
      "shape_type": "polygon",
      "flags": {}
    },
    {
      "label": "y",
      "points": [
        [
          1920,
          49
        ],
        [
          1839,
          164
        ],
        [
          1674,
          358
        ],
        [
          1466,
          565
        ],
        [
          1476,
          697
        ],
        [
          1473,
          871
        ],
        [
          1761,
          851
        ],
        [
          1920,
          828
        ],
        [
          1920,
          49
        ]
      ],
      "group_id": null,
      "shape_type": "polygon",
      "flags": {}
    },
    {
      "label": "x",
      "points": [
        [
          0,
          1080
        ],
        [
          1920,
          1080
        ],
        [
          1920,
          830
        ],
        [
          1760,
          850
        ],
        [
          1474,
          871
        ],
        [
          1167,
          895
        ],
        [
          835,
          874
        ],
        [
          465,
          858
        ],
        [
          171,
          820
        ],
        [
          0,
          782
        ],
        [
          0,
          1080
        ]
      ],
      "group_id": null,
      "shape_type": "polygon",
      "flags": {}
    }
  ],
  "imagePath": "14-8.jpg",
  "imageData": null,
  "imageHeight": 1080,
  "imageWidth": 1920
}