{
  "version": "5.1.0",
  "flags": {},
  "shapes": [
    {
      "label": "z",
      "points": [
        [
          1098,
          0
        ],
        [
          1101,
          57
        ],
        [
          1372,
          320
        ],
        [
          1598,
          102
        ],
        [
          1686,
          0
        ],
        [
          1098,
          0
        ]
      ],
      "group_id": null,
      "shape_type": "polygon",
      "flags": {}
    },
    {
      "label": "zx",
      "points": [
        [
          969,
          0
        ],
        [
          990,
          79
        ],
        [
          1100,
          56
        ],
        [
          1097,
          0
        ],
        [
          969,
          0
        ]
      ],
      "group_id": null,
      "shape_type": "polygon",
      "flags": {}
    },
    {
      "label": "s",
      "points": [
        [
          0,
          485
        ],
        [
          492,
          540
        ],
        [
          988,
          80
        ],
        [
          968,
          0
        ],
        [
          391,
          0
        ],
        [
          0,
          312
        ],
        [
          0,
          485
        ]
      ],
      "group_id": null,
      "shape_type": "polygon",
      "flags": {}
    },
    {
      "label": "yx",
      "points": [
        [
          0,
          675
        ],
        [
          461,
          652
        ],
        [
          480,
          541
        ],
        [
          0,
          486
        ],
        [
          0,
          675
        ]
      ],
      "group_id": null,
      "shape_type": "polygon",
      "flags": {}
    },
    {
      "label": "y",
      "points": [
        [
          0,
          1080
        ],
        [
          523,
          1080
        ],
        [
          690,
          939
        ],
        [
          446,
          652
        ],
        [
          0,
          675
        ],
        [
          0,
          1080
        ]
      ],
      "group_id": null,
      "shape_type": "polygon",
      "flags": {}
    },
    {
      "label": "x",
      "points": [
        [
          856,
          1080
        ],
        [
          1920,
          229
        ],
        [
          1920,
          191
        ],
        [
          1760,
          0
        ],
        [
          1687,
          0
        ],
        [
          1596,
          106
        ],
        [
          1374,
          320
        ],
        [
          1081,
          631
        ],
        [
          692,
          939
        ],
        [
          524,
          1080
        ],
        [
          856,
          1080
        ]
      ],
      "group_id": null,
      "shape_type": "polygon",
      "flags": {}
    }
  ],
  "imagePath": "15-6.jpg",
  "imageData": null,
  "imageHeight": 1080,
  "imageWidth": 1920
}