{
  "version": "5.1.0",
  "flags": {},
  "shapes": [
    {
      "label": "z",
      "points": [
        [
          1269,
          0
        ],
        [
          1273,
          17
        ],
        [
          1640,
          357
        ],
        [
          1734,
          242
        ],
        [
          1853,
          65
        ],
        [
          1889,
          0
        ],
        [
          1269,
          0
        ]
      ],
      "group_id": null,
      "shape_type": "polygon",
      "flags": {}
    },
    {
      "label": "zx",
      "points": [
        [
          1145,
          0
        ],
        [
          1180,
          94
        ],
        [
          1291,
          108
        ],
        [
          1272,
          21
        ],
        [
          1268,
          0
        ],
        [
          1145,
          0
        ]
      ],
      "group_id": null,
      "shape_type": "polygon",
      "flags": {}
    },
    {
      "label": "s",
      "points": [
        [
          674,
          0
        ],
        [
          331,
          356
        ],
        [
          590,
          446
        ],
        [
          798,
          512
        ],
        [
          1180,
          97
        ],
        [
          1144,
          0
        ],
        [
          674,
          0
        ]
      ],
      "group_id": null,
      "shape_type": "polygon",
      "flags": {}
    },
    {
      "label": "yx",
      "points": [
        [
          591,
          447
        ],
        [
          331,
          356
        ],
        [
          183,
          510
        ],
        [
          576,
          593
        ],
        [
          788,
          618
        ],
        [
          765,
          501
        ],
        [
          591,
          447
        ]
      ],
      "group_id": null,
      "shape_type": "polygon",
      "flags": {}
    },
    {
      "label": "y",
      "points": [
        [
          929,
          1080
        ],
        [
          1040,
          981
        ],
        [
          803,
          722
        ],
        [
          718,
          611
        ],
        [
          577,
          596
        ],
        [
          183,
          509
        ],
        [
          170,
          523
        ],
        [
          694,
          1080
        ],
        [
          929,
          1080
        ]
      ],
      "group_id": null,
      "shape_type": "polygon",
      "flags": {}
    },
    {
      "label": "x",
      "points": [
        [
          1268,
          1080
        ],
        [
          1920,
          403
        ],
        [
          1920,
          0
        ],
        [
          1889,
          0
        ],
        [
          1853,
          66
        ],
        [
          1732,
          243
        ],
        [
          1640,
          356
        ],
        [
          1436,
          640
        ],
        [
          1357,
          727
        ],
        [
          1041,
          982
        ],
        [
          930,
          1080
        ],
        [
          1268,
          1080
        ]
      ],
      "group_id": null,
      "shape_type": "polygon",
      "flags": {}
    }
  ],
  "imagePath": "19-4.jpg",
  "imageData": null,
  "imageHeight": 1080,
  "imageWidth": 1920
}