{
  "version": "5.1.0",
  "flags": {},
  "shapes": [
    {
      "label": "zx",
      "points": [
        [
          295,
          0
        ],
        [
          554,
          366
        ],
        [
          653,
          268
        ],
        [
          530,
          0
        ],
        [
          295,
          0
        ]
      ],
      "group_id": null,
      "shape_type": "polygon",
      "flags": {}
    },
    {
      "label": "z",
      "points": [
        [
          0,
          843
        ],
        [
          323,
          912
        ],
        [
          436,
          923
        ],
        [
          436,
          866
        ],
        [
          450,
          688
        ],
        [
          481,
          455
        ],
        [
          505,
          302
        ],
        [
          294,
          0
        ],
        [
          0,
          0
        ],
        [
          0,
          843
        ]
      ],
      "group_id": null,
      "shape_type": "polygon",
      "flags": {}
    },
    {
      "label": "s",
      "points": [
        [
          530,
          0
        ],
        [
          654,
          269
        ],
        [
          1433,
          319
        ],
        [
          1569,
          98
        ],
        [
          1622,
          0
        ],
        [
          530,
          0
        ]
      ],
      "group_id": null,
      "shape_type": "polygon",
      "flags": {}
    },
    {
      "label": "yx",
      "points": [
        [
          1622,
          0
        ],
        [
          1562,
          112
        ],
        [
          1413,
          355
        ],
        [
          1497,
          453
        ],
        [
          1657,
          274
        ],
        [
          1826,
          60
        ],
        [
          1867,
          0
        ],
        [
          1622,
          0
        ]
      ],
      "group_id": null,
      "shape_type": "polygon",
      "flags": {}
    },
    {
      "label": "y",
      "points": [
        [
          1920,
          0
        ],
        [
          1868,
          0
        ],
        [
          1810,
          82
        ],
        [
          1479,
          479
        ],
        [
          1488,
          595
        ],
        [
          1496,
          822
        ],
        [
          1489,
          968
        ],
        [
          1755,
          952
        ],
        [
          1920,
          934
        ],
        [
          1920,
          0
        ]
      ],
      "group_id": null,
      "shape_type": "polygon",
      "flags": {}
    },
    {
      "label": "x",
      "points": [
        [
          0,
          1080
        ],
        [
          1920,
          1080
        ],
        [
          1920,
          933
        ],
        [
          1755,
          955
        ],
        [
          1487,
          970
        ],
        [
          1289,
          1013
        ],
        [
          822,
          1007
        ],
        [
          660,
          999
        ],
        [
          435,
          923
        ],
        [
          321,
          914
        ],
        [
          0,
          848
        ],
        [
          0,
          1080
        ]
      ],
      "group_id": null,
      "shape_type": "polygon",
      "flags": {}
    }
  ],
  "imagePath": "28-11.jpg",
  "imageData": null,
  "imageHeight": 1080,
  "imageWidth": 1920
}