{
  "version": "5.1.0",
  "flags": {},
  "shapes": [
    {
      "label": "z",
      "points": [
        [
          1196,
          1080
        ],
        [
          1235,
          1039
        ],
        [
          1000,
          811
        ],
        [
          850,
          648
        ],
        [
          623,
          615
        ],
        [
          451,
          584
        ],
        [
          282,
          794
        ],
        [
          627,
          1080
        ],
        [
          1196,
          1080
        ]
      ],
      "group_id": null,
      "shape_type": "polygon",
      "flags": {}
    },
    {
      "label": "zx",
      "points": [
        [
          852,
          651
        ],
        [
          846,
          520
        ],
        [
          628,
          453
        ],
        [
          570,
          433
        ],
        [
          450,
          583
        ],
        [
          660,
          621
        ],
        [
          852,
          651
        ]
      ],
      "group_id": null,
      "shape_type": "polygon",
      "flags": {}
    },
    {
      "label": "s",
      "points": [
        [
          914,
          0
        ],
        [
          570,
          432
        ],
        [
          844,
          519
        ],
        [
          1074,
          239
        ],
        [
          1286,
          10
        ],
        [
          1281,
          0
        ],
        [
          914,
          0
        ]
      ],
      "group_id": null,
      "shape_type": "polygon",
      "flags": {}
    },
    {
      "label": "yx",
      "points": [
        [
          1282,
          0
        ],
        [
          1286,
          9
        ],
        [
          1413,
          4
        ],
        [
          1412,
          0
        ],
        [
          1282,
          0
        ]
      ],
      "group_id": null,
      "shape_type": "polygon",
      "flags": {}
    },
    {
      "label": "y",
      "points": [
        [
          1920,
          0
        ],
        [
          1413,
          0
        ],
        [
          1415,
          7
        ],
        [
          1513,
          71
        ],
        [
          1835,
          338
        ],
        [
          1916,
          227
        ],
        [
          1920,
          220
        ],
        [
          1920,
          0
        ]
      ],
      "group_id": null,
      "shape_type": "polygon",
      "flags": {}
    },
    {
      "label": "x",
      "points": [
        [
          1519,
          1080
        ],
        [
          1920,
          576
        ],
        [
          1920,
          221
        ],
        [
          1918,
          225
        ],
        [
          1836,
          338
        ],
        [
          1799,
          426
        ],
        [
          1635,
          649
        ],
        [
          1437,
          876
        ],
        [
          1237,
          1037
        ],
        [
          1198,
          1080
        ],
        [
          1519,
          1080
        ]
      ],
      "group_id": null,
      "shape_type": "polygon",
      "flags": {}
    }
  ],
  "imagePath": "37-3.jpg",
  "imageData": null,
  "imageHeight": 1080,
  "imageWidth": 1920
}