{
  "version": "5.1.0",
  "flags": {},
  "shapes": [
    {
      "label": "z",
      "points": [
        [
          874,
          0
        ],
        [
          896,
          150
        ],
        [
          1211,
          690
        ],
        [
          1353,
          628
        ],
        [
          1564,
          512
        ],
        [
          1897,
          272
        ],
        [
          1748,
          0
        ],
        [
          874,
          0
        ]
      ],
      "group_id": null,
      "shape_type": "polygon",
      "flags": {}
    },
    {
      "label": "zx",
      "points": [
        [
          725,
          0
        ],
        [
          782,
          164
        ],
        [
          900,
          197
        ],
        [
          873,
          0
        ],
        [
          725,
          0
        ]
      ],
      "group_id": null,
      "shape_type": "polygon",
      "flags": {}
    },
    {
      "label": "s",
      "points": [
        [
          0,
          378
        ],
        [
          50,
          411
        ],
        [
          240,
          501
        ],
        [
          781,
          163
        ],
        [
          725,
          0
        ],
        [
          381,
          0
        ],
        [
          0,
          210
        ],
        [
          0,
          378
        ]
      ],
      "group_id": null,
      "shape_type": "polygon",
      "flags": {}
    },
    {
      "label": "yx",
      "points": [
        [
          0,
          538
        ],
        [
          127,
          594
        ],
        [
          304,
          645
        ],
        [
          315,
          538
        ],
        [
          49,
          410
        ],
        [
          0,
          377
        ],
        [
          0,
          538
        ]
      ],
      "group_id": null,
      "shape_type": "polygon",
      "flags": {}
    },
    {
      "label": "y",
      "points": [
        [
          0,
          618
        ],
        [
          250,
          1080
        ],
        [
          403,
          1080
        ],
        [
          410,
          1078
        ],
        [
          486,
          1044
        ],
        [
          332,
          745
        ],
        [
          296,
          646
        ],
        [
          127,
          596
        ],
        [
          0,
          539
        ],
        [
          0,
          618
        ]
      ],
      "group_id": null,
      "shape_type": "polygon",
      "flags": {}
    },
    {
      "label": "x",
      "points": [
        [
          984,
          1080
        ],
        [
          1920,
          563
        ],
        [
          1920,
          314
        ],
        [
          1896,
          271
        ],
        [
          1564,
          512
        ],
        [
          1353,
          628
        ],
        [
          1211,
          690
        ],
        [
          982,
          837
        ],
        [
          667,
          988
        ],
        [
          488,
          1047
        ],
        [
          410,
          1079
        ],
        [
          406,
          1080
        ],
        [
          984,
          1080
        ]
      ],
      "group_id": null,
      "shape_type": "polygon",
      "flags": {}
    }
  ],
  "imagePath": "60-7.jpg",
  "imageData": null,
  "imageHeight": 1080,
  "imageWidth": 1920
}