{
  "version": "5.1.0",
  "flags": {},
  "shapes": [
    {
      "label": "z",
      "points": [
        [
          0,
          816
        ],
        [
          117,
          842
        ],
        [
          159,
          461
        ],
        [
          192,
          351
        ],
        [
          56,
          161
        ],
        [
          0,
          64
        ],
        [
          0,
          816
        ]
      ],
      "group_id": null,
      "shape_type": "polygon",
      "flags": {}
    },
    {
      "label": "zx",
      "points": [
        [
          0,
          62
        ],
        [
          55,
          157
        ],
        [
          203,
          360
        ],
        [
          296,
          279
        ],
        [
          206,
          98
        ],
        [
          162,
          0
        ],
        [
          0,
          0
        ],
        [
          0,
          62
        ]
      ],
      "group_id": null,
      "shape_type": "polygon",
      "flags": {}
    },
    {
      "label": "s",
      "points": [
        [
          165,
          0
        ],
        [
          207,
          100
        ],
        [
          283,
          247
        ],
        [
          1043,
          288
        ],
        [
          1173,
          86
        ],
        [
          1229,
          0
        ],
        [
          165,
          0
        ]
      ],
      "group_id": null,
      "shape_type": "polygon",
      "flags": {}
    },
    {
      "label": "yx",
      "points": [
        [
          1228,
          0
        ],
        [
          1080,
          233
        ],
        [
          1190,
          349
        ],
        [
          1498,
          0
        ],
        [
          1228,
          0
        ]
      ],
      "group_id": null,
      "shape_type": "polygon",
      "flags": {}
    },
    {
      "label": "y",
      "points": [
        [
          1920,
          0
        ],
        [
          1499,
          0
        ],
        [
          1279,
          251
        ],
        [
          1292,
          414
        ],
        [
          1304,
          648
        ],
        [
          1282,
          948
        ],
        [
          1495,
          945
        ],
        [
          1920,
          896
        ],
        [
          1920,
          0
        ]
      ],
      "group_id": null,
      "shape_type": "polygon",
      "flags": {}
    },
    {
      "label": "x",
      "points": [
        [
          0,
          1080
        ],
        [
          1920,
          1080
        ],
        [
          1920,
          896
        ],
        [
          1494,
          944
        ],
        [
          1281,
          946
        ],
        [
          1020,
          964
        ],
        [
          660,
          946
        ],
        [
          329,
          897
        ],
        [
          117,
          840
        ],
        [
          0,
          816
        ],
        [
          0,
          1080
        ]
      ],
      "group_id": null,
      "shape_type": "polygon",
      "flags": {}
    }
  ],
  "imagePath": "64-15.jpg",
  "imageData": null,
  "imageHeight": 1080,
  "imageWidth": 1920
}