{
  "version": "5.1.0",
  "flags": {},
  "shapes": [
    {
      "label": "zx",
      "points": [
        [
          1794,
          616
        ],
        [
          1546,
          719
        ],
        [
          1551,
          819
        ],
        [
          1770,
          765
        ],
        [
          1908,
          713
        ],
        [
          1794,
          616
        ]
      ],
      "group_id": null,
      "shape_type": "polygon",
      "flags": {}
    },
    {
      "label": "s",
      "points": [
        [
          1794,
          616
        ],
        [
          1199,
          107
        ],
        [
          1116,
          334
        ],
        [
          1592,
          701
        ],
        [
          1794,
          616
        ]
      ],
      "group_id": null,
      "shape_type": "polygon",
      "flags": {}
    },
    {
      "label": "yx",
      "points": [
        [
          1057,
          0
        ],
        [
          983,
          388
        ],
        [
          1108,
          352
        ],
        [
          1199,
          108
        ],
        [
          1072,
          0
        ],
        [
          1057,
          0
        ]
      ],
      "group_id": null,
      "shape_type": "polygon",
      "flags": {}
    },
    {
      "label": "y",
      "points": [
        [
          463,
          0
        ],
        [
          179,
          338
        ],
        [
          461,
          606
        ],
        [
          677,
          763
        ],
        [
          985,
          374
        ],
        [
          1056,
          0
        ],
        [
          463,
          0
        ]
      ],
      "group_id": null,
      "shape_type": "polygon",
      "flags": {}
    },
    {
      "label": "z",
      "points": [
        [
          1609,
          1080
        ],
        [
          1914,
          718
        ],
        [
          1907,
          713
        ],
        [
          1771,
          765
        ],
        [
          1573,
          814
        ],
        [
          1527,
          903
        ],
        [
          1414,
          1080
        ],
        [
          1609,
          1080
        ]
      ],
      "group_id": null,
      "shape_type": "polygon",
      "flags": {}
    },
    {
      "label": "x",
      "points": [
        [
          1109,
          1080
        ],
        [
          1052,
          1053
        ],
        [
          749,
          832
        ],
        [
          679,
          764
        ],
        [
          463,
          607
        ],
        [
          179,
          338
        ],
        [
          71,
          467
        ],
        [
          787,
          1080
        ],
        [
          1109,
          1080
        ]
      ],
      "group_id": null,
      "shape_type": "polygon",
      "flags": {}
    }
  ],
  "imagePath": "66-15.jpg",
  "imageData": null,
  "imageHeight": 1080,
  "imageWidth": 1920
}