{
  "version": "5.1.0",
  "flags": {},
  "shapes": [
    {
      "label": "zx",
      "points": [
        [
          0,
          24
        ],
        [
          120,
          198
        ],
        [
          220,
          329
        ],
        [
          280,
          391
        ],
        [
          353,
          321
        ],
        [
          243,
          133
        ],
        [
          169,
          1
        ],
        [
          0,
          0
        ],
        [
          0,
          24
        ]
      ],
      "group_id": null,
      "shape_type": "polygon",
      "flags": {}
    },
    {
      "label": "z",
      "points": [
        [
          0,
          758
        ],
        [
          213,
          801
        ],
        [
          252,
          482
        ],
        [
          270,
          383
        ],
        [
          222,
          333
        ],
        [
          121,
          199
        ],
        [
          0,
          22
        ],
        [
          0,
          758
        ]
      ],
      "group_id": null,
      "shape_type": "polygon",
      "flags": {}
    },
    {
      "label": "s",
      "points": [
        [
          170,
          0
        ],
        [
          246,
          135
        ],
        [
          338,
          299
        ],
        [
          980,
          320
        ],
        [
          1087,
          79
        ],
        [
          1121,
          0
        ],
        [
          170,
          0
        ]
      ],
      "group_id": null,
      "shape_type": "polygon",
      "flags": {}
    },
    {
      "label": "yx",
      "points": [
        [
          1122,
          0
        ],
        [
          995,
          286
        ],
        [
          1091,
          381
        ],
        [
          1348,
          0
        ],
        [
          1122,
          0
        ]
      ],
      "group_id": null,
      "shape_type": "polygon",
      "flags": {}
    },
    {
      "label": "y",
      "points": [
        [
          1920,
          0
        ],
        [
          1349,
          0
        ],
        [
          1147,
          296
        ],
        [
          1128,
          904
        ],
        [
          1315,
          919
        ],
        [
          1549,
          926
        ],
        [
          1920,
          892
        ],
        [
          1920,
          0
        ]
      ],
      "group_id": null,
      "shape_type": "polygon",
      "flags": {}
    },
    {
      "label": "x",
      "points": [
        [
          0,
          1080
        ],
        [
          1920,
          1080
        ],
        [
          1920,
          893
        ],
        [
          1549,
          925
        ],
        [
          1316,
          918
        ],
        [
          1127,
          905
        ],
        [
          728,
          896
        ],
        [
          451,
          855
        ],
        [
          214,
          801
        ],
        [
          0,
          758
        ],
        [
          0,
          1080
        ]
      ],
      "group_id": null,
      "shape_type": "polygon",
      "flags": {}
    }
  ],
  "imagePath": "68-7.jpg",
  "imageData": null,
  "imageHeight": 1080,
  "imageWidth": 1920
}