{
  "version": "5.1.0",
  "flags": {},
  "shapes": [
    {
      "label": "z",
      "points": [
        [
          1920,
          0
        ],
        [
          1849,
          0
        ],
        [
          1776,
          128
        ],
        [
          1631,
          326
        ],
        [
          1481,
          500
        ],
        [
          1514,
          817
        ],
        [
          1736,
          783
        ],
        [
          1920,
          748
        ],
        [
          1920,
          0
        ]
      ],
      "group_id": null,
      "shape_type": "polygon",
      "flags": {}
    },
    {
      "label": "zx",
      "points": [
        [
          1645,
          0
        ],
        [
          1546,
          207
        ],
        [
          1414,
          447
        ],
        [
          1480,
          500
        ],
        [
          1627,
          326
        ],
        [
          1775,
          129
        ],
        [
          1849,
          0
        ],
        [
          1645,
          0
        ]
      ],
      "group_id": null,
      "shape_type": "polygon",
      "flags": {}
    },
    {
      "label": "s",
      "points": [
        [
          572,
          0
        ],
        [
          745,
          251
        ],
        [
          892,
          466
        ],
        [
          1421,
          432
        ],
        [
          1543,
          208
        ],
        [
          1644,
          0
        ],
        [
          572,
          0
        ]
      ],
      "group_id": null,
      "shape_type": "polygon",
      "flags": {}
    },
    {
      "label": "yx",
      "points": [
        [
          278,
          0
        ],
        [
          760,
          474
        ],
        [
          846,
          398
        ],
        [
          573,
          0
        ],
        [
          278,
          0
        ]
      ],
      "group_id": null,
      "shape_type": "polygon",
      "flags": {}
    },
    {
      "label": "y",
      "points": [
        [
          0,
          849
        ],
        [
          67,
          862
        ],
        [
          398,
          891
        ],
        [
          754,
          881
        ],
        [
          749,
          462
        ],
        [
          529,
          249
        ],
        [
          278,
          0
        ],
        [
          0,
          0
        ],
        [
          0,
          849
        ]
      ],
      "group_id": null,
      "shape_type": "polygon",
      "flags": {}
    },
    {
      "label": "x",
      "points": [
        [
          0,
          1080
        ],
        [
          1920,
          1080
        ],
        [
          1920,
          750
        ],
        [
          1739,
          781
        ],
        [
          1514,
          814
        ],
        [
          1140,
          875
        ],
        [
          754,
          881
        ],
        [
          399,
          893
        ],
        [
          67,
          862
        ],
        [
          0,
          849
        ],
        [
          0,
          1080
        ]
      ],
      "group_id": null,
      "shape_type": "polygon",
      "flags": {}
    }
  ],
  "imagePath": "7-18.jpg",
  "imageData": null,
  "imageHeight": 1080,
  "imageWidth": 1920
}