{
  "version": "5.1.0",
  "flags": {},
  "shapes": [
    {
      "label": "z",
      "points": [
        [
          1920,
          0
        ],
        [
          1574,
          0
        ],
        [
          1341,
          259
        ],
        [
          1366,
          410
        ],
        [
          1393,
          629
        ],
        [
          1405,
          870
        ],
        [
          1532,
          858
        ],
        [
          1700,
          834
        ],
        [
          1920,
          797
        ],
        [
          1920,
          0
        ]
      ],
      "group_id": null,
      "shape_type": "polygon",
      "flags": {}
    },
    {
      "label": "zx",
      "points": [
        [
          1305,
          0
        ],
        [
          1178,
          214
        ],
        [
          1287,
          316
        ],
        [
          1571,
          0
        ],
        [
          1305,
          0
        ]
      ],
      "group_id": null,
      "shape_type": "polygon",
      "flags": {}
    },
    {
      "label": "s",
      "points": [
        [
          207,
          0
        ],
        [
          327,
          237
        ],
        [
          1160,
          243
        ],
        [
          1304,
          0
        ],
        [
          207,
          0
        ]
      ],
      "group_id": null,
      "shape_type": "polygon",
      "flags": {}
    },
    {
      "label": "yx",
      "points": [
        [
          0,
          51
        ],
        [
          47,
          120
        ],
        [
          203,
          318
        ],
        [
          314,
          216
        ],
        [
          206,
          0
        ],
        [
          0,
          0
        ],
        [
          0,
          51
        ]
      ],
      "group_id": null,
      "shape_type": "polygon",
      "flags": {}
    },
    {
      "label": "y",
      "points": [
        [
          0,
          872
        ],
        [
          249,
          890
        ],
        [
          245,
          803
        ],
        [
          242,
          656
        ],
        [
          250,
          516
        ],
        [
          265,
          393
        ],
        [
          144,
          243
        ],
        [
          45,
          116
        ],
        [
          0,
          49
        ],
        [
          0,
          872
        ]
      ],
      "group_id": null,
      "shape_type": "polygon",
      "flags": {}
    },
    {
      "label": "x",
      "points": [
        [
          0,
          1080
        ],
        [
          1920,
          1080
        ],
        [
          1920,
          798
        ],
        [
          1537,
          860
        ],
        [
          1404,
          870
        ],
        [
          1269,
          906
        ],
        [
          1077,
          935
        ],
        [
          896,
          936
        ],
        [
          737,
          942
        ],
        [
          558,
          934
        ],
        [
          412,
          921
        ],
        [
          251,
          890
        ],
        [
          0,
          873
        ],
        [
          0,
          1080
        ]
      ],
      "group_id": null,
      "shape_type": "polygon",
      "flags": {}
    }
  ],
  "imagePath": "74-2.jpg",
  "imageData": null,
  "imageHeight": 1080,
  "imageWidth": 1920
}