{
  "version": "5.1.0",
  "flags": {},
  "shapes": [
    {
      "label": "z",
      "points": [
        [
          1920,
          0
        ],
        [
          1859,
          0
        ],
        [
          1846,
          69
        ],
        [
          1781,
          283
        ],
        [
          1728,
          437
        ],
        [
          1767,
          543
        ],
        [
          1866,
          876
        ],
        [
          1920,
          859
        ],
        [
          1920,
          0
        ]
      ],
      "group_id": null,
      "shape_type": "polygon",
      "flags": {}
    },
    {
      "label": "zx",
      "points": [
        [
          1682,
          0
        ],
        [
          1660,
          4
        ],
        [
          1642,
          192
        ],
        [
          1621,
          376
        ],
        [
          1728,
          439
        ],
        [
          1835,
          99
        ],
        [
          1857,
          0
        ],
        [
          1682,
          0
        ]
      ],
      "group_id": null,
      "shape_type": "polygon",
      "flags": {}
    },
    {
      "label": "s",
      "points": [
        [
          1660,
          4
        ],
        [
          498,
          209
        ],
        [
          947,
          570
        ],
        [
          1333,
          449
        ],
        [
          1620,
          373
        ],
        [
          1660,
          4
        ]
      ],
      "group_id": null,
      "shape_type": "polygon",
      "flags": {}
    },
    {
      "label": "yx",
      "points": [
        [
          499,
          209
        ],
        [
          179,
          266
        ],
        [
          446,
          431
        ],
        [
          789,
          626
        ],
        [
          868,
          508
        ],
        [
          499,
          209
        ]
      ],
      "group_id": null,
      "shape_type": "polygon",
      "flags": {}
    },
    {
      "label": "y",
      "points": [
        [
          798,
          1080
        ],
        [
          731,
          715
        ],
        [
          717,
          585
        ],
        [
          445,
          429
        ],
        [
          179,
          266
        ],
        [
          23,
          294
        ],
        [
          169,
          1080
        ],
        [
          798,
          1080
        ]
      ],
      "group_id": null,
      "shape_type": "polygon",
      "flags": {}
    },
    {
      "label": "x",
      "points": [
        [
          1920,
          1080
        ],
        [
          1920,
          858
        ],
        [
          1869,
          874
        ],
        [
          1616,
          982
        ],
        [
          1356,
          1057
        ],
        [
          1252,
          1080
        ],
        [
          1920,
          1080
        ]
      ],
      "group_id": null,
      "shape_type": "polygon",
      "flags": {}
    }
  ],
  "imagePath": "80-14.jpg",
  "imageData": null,
  "imageHeight": 1080,
  "imageWidth": 1920
}