{
  "version": "5.1.0",
  "flags": {},
  "shapes": [
    {
      "label": "z",
      "points": [
        [
          1920,
          0
        ],
        [
          1696,
          1
        ],
        [
          1570,
          163
        ],
        [
          1398,
          371
        ],
        [
          1431,
          478
        ],
        [
          1467,
          854
        ],
        [
          1554,
          846
        ],
        [
          1839,
          801
        ],
        [
          1920,
          784
        ],
        [
          1920,
          0
        ]
      ],
      "group_id": null,
      "shape_type": "polygon",
      "flags": {}
    },
    {
      "label": "zx",
      "points": [
        [
          1466,
          0
        ],
        [
          1286,
          323
        ],
        [
          1371,
          404
        ],
        [
          1696,
          0
        ],
        [
          1466,
          0
        ]
      ],
      "group_id": null,
      "shape_type": "polygon",
      "flags": {}
    },
    {
      "label": "s",
      "points": [
        [
          377,
          0
        ],
        [
          468,
          172
        ],
        [
          574,
          344
        ],
        [
          1284,
          323
        ],
        [
          1464,
          0
        ],
        [
          377,
          0
        ]
      ],
      "group_id": null,
      "shape_type": "polygon",
      "flags": {}
    },
    {
      "label": "yx",
      "points": [
        [
          142,
          0
        ],
        [
          260,
          166
        ],
        [
          512,
          465
        ],
        [
          591,
          378
        ],
        [
          468,
          174
        ],
        [
          376,
          0
        ],
        [
          142,
          0
        ]
      ],
      "group_id": null,
      "shape_type": "polygon",
      "flags": {}
    },
    {
      "label": "y",
      "points": [
        [
          0,
          846
        ],
        [
          277,
          885
        ],
        [
          389,
          883
        ],
        [
          383,
          756
        ],
        [
          397,
          486
        ],
        [
          416,
          354
        ],
        [
          260,
          167
        ],
        [
          141,
          0
        ],
        [
          0,
          0
        ],
        [
          0,
          846
        ]
      ],
      "group_id": null,
      "shape_type": "polygon",
      "flags": {}
    },
    {
      "label": "x",
      "points": [
        [
          0,
          1080
        ],
        [
          1920,
          1080
        ],
        [
          1920,
          784
        ],
        [
          1841,
          800
        ],
        [
          1554,
          846
        ],
        [
          1467,
          855
        ],
        [
          1075,
          905
        ],
        [
          595,
          916
        ],
        [
          389,
          883
        ],
        [
          276,
          886
        ],
        [
          0,
          847
        ],
        [
          0,
          1080
        ]
      ],
      "group_id": null,
      "shape_type": "polygon",
      "flags": {}
    }
  ],
  "imagePath": "84-19.jpg",
  "imageData": null,
  "imageHeight": 1080,
  "imageWidth": 1920
}