{
  "version": "5.1.0",
  "flags": {},
  "shapes": [
    {
      "label": "z",
      "points": [
        [
          0,
          889
        ],
        [
          200,
          928
        ],
        [
          378,
          954
        ],
        [
          527,
          964
        ],
        [
          548,
          619
        ],
        [
          568,
          448
        ],
        [
          597,
          270
        ],
        [
          510,
          126
        ],
        [
          446,
          0
        ],
        [
          0,
          0
        ],
        [
          0,
          889
        ]
      ],
      "group_id": null,
      "shape_type": "polygon",
      "flags": {}
    },
    {
      "label": "zx",
      "points": [
        [
          447,
          0
        ],
        [
          510,
          126
        ],
        [
          600,
          275
        ],
        [
          638,
          349
        ],
        [
          756,
          252
        ],
        [
          682,
          0
        ],
        [
          447,
          0
        ]
      ],
      "group_id": null,
      "shape_type": "polygon",
      "flags": {}
    },
    {
      "label": "s",
      "points": [
        [
          683,
          0
        ],
        [
          747,
          217
        ],
        [
          1147,
          227
        ],
        [
          1292,
          231
        ],
        [
          1574,
          273
        ],
        [
          1749,
          0
        ],
        [
          683,
          0
        ]
      ],
      "group_id": null,
      "shape_type": "polygon",
      "flags": {}
    },
    {
      "label": "yx",
      "points": [
        [
          1920,
          0
        ],
        [
          1746,
          0
        ],
        [
          1573,
          276
        ],
        [
          1491,
          384
        ],
        [
          1570,
          486
        ],
        [
          1739,
          304
        ],
        [
          1886,
          127
        ],
        [
          1920,
          77
        ],
        [
          1920,
          0
        ]
      ],
      "group_id": null,
      "shape_type": "polygon",
      "flags": {}
    },
    {
      "label": "y",
      "points": [
        [
          1920,
          78
        ],
        [
          1886,
          130
        ],
        [
          1736,
          308
        ],
        [
          1592,
          465
        ],
        [
          1605,
          587
        ],
        [
          1615,
          776
        ],
        [
          1616,
          950
        ],
        [
          1733,
          938
        ],
        [
          1920,
          906
        ],
        [
          1920,
          78
        ]
      ],
      "group_id": null,
      "shape_type": "polygon",
      "flags": {}
    },
    {
      "label": "x",
      "points": [
        [
          0,
          1080
        ],
        [
          1920,
          1080
        ],
        [
          1920,
          906
        ],
        [
          1730,
          937
        ],
        [
          1614,
          949
        ],
        [
          1373,
          986
        ],
        [
          983,
          994
        ],
        [
          727,
          995
        ],
        [
          527,
          964
        ],
        [
          378,
          954
        ],
        [
          199,
          928
        ],
        [
          0,
          888
        ],
        [
          0,
          1080
        ]
      ],
      "group_id": null,
      "shape_type": "polygon",
      "flags": {}
    }
  ],
  "imagePath": "92-19.jpg",
  "imageData": null,
  "imageHeight": 1080,
  "imageWidth": 1920
}