{
  "version": "5.1.0",
  "flags": {},
  "shapes": [
    {
      "label": "z",
      "points": [
        [
          0,
          593
        ],
        [
          23,
          611
        ],
        [
          144,
          679
        ],
        [
          275,
          750
        ],
        [
          370,
          551
        ],
        [
          474,
          374
        ],
        [
          553,
          243
        ],
        [
          532,
          60
        ],
        [
          529,
          0
        ],
        [
          144,
          0
        ],
        [
          0,
          334
        ],
        [
          0,
          593
        ]
      ],
      "group_id": null,
      "shape_type": "polygon",
      "flags": {}
    },
    {
      "label": "zx",
      "points": [
        [
          530,
          0
        ],
        [
          533,
          63
        ],
        [
          565,
          344
        ],
        [
          688,
          304
        ],
        [
          703,
          81
        ],
        [
          715,
          0
        ],
        [
          530,
          0
        ]
      ],
      "group_id": null,
      "shape_type": "polygon",
      "flags": {}
    },
    {
      "label": "s",
      "points": [
        [
          714,
          0
        ],
        [
          703,
          80
        ],
        [
          691,
          299
        ],
        [
          1009,
          437
        ],
        [
          1263,
          560
        ],
        [
          1650,
          286
        ],
        [
          900,
          0
        ],
        [
          714,
          0
        ]
      ],
      "group_id": null,
      "shape_type": "polygon",
      "flags": {}
    },
    {
      "label": "yx",
      "points": [
        [
          1262,
          689
        ],
        [
          1590,
          535
        ],
        [
          1704,
          471
        ],
        [
          1811,
          403
        ],
        [
          1831,
          355
        ],
        [
          1650,
          286
        ],
        [
          1388,
          475
        ],
        [
          1219,
          587
        ],
        [
          1262,
          689
        ]
      ],
      "group_id": null,
      "shape_type": "polygon",
      "flags": {}
    },
    {
      "label": "y",
      "points": [
        [
          1518,
          1080
        ],
        [
          1810,
          404
        ],
        [
          1703,
          473
        ],
        [
          1587,
          540
        ],
        [
          1368,
          642
        ],
        [
          1324,
          777
        ],
        [
          1259,
          947
        ],
        [
          1198,
          1080
        ],
        [
          1518,
          1080
        ]
      ],
      "group_id": null,
      "shape_type": "polygon",
      "flags": {}
    },
    {
      "label": "x",
      "points": [
        [
          0,
          896
        ],
        [
          479,
          1080
        ],
        [
          999,
          1080
        ],
        [
          953,
          1069
        ],
        [
          643,
          958
        ],
        [
          414,
          847
        ],
        [
          274,
          748
        ],
        [
          24,
          613
        ],
        [
          0,
          594
        ],
        [
          0,
          896
        ]
      ],
      "group_id": null,
      "shape_type": "polygon",
      "flags": {}
    }
  ],
  "imagePath": "95-9.jpg",
  "imageData": null,
  "imageHeight": 1080,
  "imageWidth": 1920
}